hankai/__init__.py
hankai/api_client/__init__.py
hankai/api_client/bin/__init__.py
hankai/api_client/bin/api_client.py
hankai/api_client/bin/mock_message.py
hankai/api_client/lib/__init__.py
hankai/api_client/lib/api_client.py
hankai/api_client/lib/api_client_argparse.py
hankai/api_client/lib/api_client_default.py
hankai/api_client/lib/api_client_executor.py
hankai/api_client/lib/autocoding_api_response.py
hankai/api_client/lib/docuvision_api_response.py
hankai/api_client/lib/docuvision_transform_facesheet.py
hankai/api_client/lib/docuvision_transform_facesheet_csv_argparse.py
hankai/api_client/lib/docuvision_transform_facesheet_csv_default.py
hankai/api_client/lib/docuvision_transform_facesheet_csv_parser.py
hankai/api_client/lib/enum_other.py
hankai/api_client/lib/mock_message_argparse.py
hankai/api_client/lib/mock_message_default.py
hankai/api_client/lib/transform.py
hank_ai_api_client-3.2.3.dist-info/METADATA
hank_ai_api_client-3.2.3.dist-info/WHEEL
hank_ai_api_client-3.2.3.dist-info/entry_points.txt
hank_ai_api_client-3.2.3.dist-info/namespace_packages.txt
hank_ai_api_client-3.2.3.dist-info/top_level.txt
hank_ai_api_client-3.2.3.dist-info/RECORD
